{
  "schemaVersion": null,
  "schemaName": "dbo, salesLT",
  "migrations": [
    {
      "category": "Versioned",
      "version": "003.20230224210757",
      "description": "BMac",
      "type": "SQL",
      "installedOnUTC": "",
      "state": "Pending",
      "undoable": "No",
      "filepath": "C:\\Users\\BMac\\actions-runner-comm\\_work\\AdvWorksComm\\AdvWorksComm\\migrations\\V003_20230224210757__BMac.sql",
      "undoFilepath": "",
      "installedBy": "",
      "executionTime": 0
    }
  ],
  "allSchemasEmpty": false,
  "flywayVersion": "9.15.1",
  "database": "AdvWorksComm",
  "warnings": [],
  "operation": "info"
}
